[
	{
		"names": [
			"LC(DOWN)"
		],
		"description": "LC(DOWN)",
		"clarify": false,
		"documentation": "",
		"os": {
			"windows": true,
			"linux": true,
			"android": true,
			"macos": true,
			"ios": true
		},
		"footnotes": {},
		"type": "UD"
	},
	{
		"names": [
			"LA(RG(ESC))"
		],
		"description": "LA(RG(ESC))",
		"clarify": false,
		"documentation": "",
		"os": {
			"windows": true,
			"linux": true,
			"android": true,
			"macos": true,
			"ios": true
		},
		"footnotes": {},
		"type": "UD"
	}
]